pshlib/__init__.py
pshlib/psh.py
pshlib/shcmd.py
pshlib-0.1.1.dist-info/LICENSE
pshlib-0.1.1.dist-info/METADATA
pshlib-0.1.1.dist-info/WHEEL
pshlib-0.1.1.dist-info/RECORD
