Metadata-Version: 2.1
Name: pshlib
Version: 0.1.1
Summary: Causal embedding of shell commands into python code.
Home-page: https://gitlab.com/ewiger/pshlib
Author: Yauhen Yakimovich
Author-email: yauhen.yakimovich.mail@gmail.com
Requires-Python: >=3.9,<4.0
Classifier: Programming Language :: Python :: 3
Classifier: Programming Language :: Python :: 3.9
Classifier: Programming Language :: Python :: 3.10
Classifier: Programming Language :: Python :: 3.11
